as_cli.py
appsentinels_cli-2.2.8.dist-info/licenses/LICENSE
src/__init__.py
src/config.py
src/post_install.py
src/commands/__init__.py
src/commands/auth_handler.py
src/commands/init_handler.py
src/commands/plugin_handler.py
src/commands/profile_handler.py
src/core/__init__.py
src/core/auth_context.py
src/core/base_handler.py
src/core/cli_processor.py
src/core/plugin_interface.py
src/core/plugin_manager.py
appsentinels_cli-2.2.8.dist-info/METADATA
appsentinels_cli-2.2.8.dist-info/WHEEL
appsentinels_cli-2.2.8.dist-info/entry_points.txt
appsentinels_cli-2.2.8.dist-info/top_level.txt
appsentinels_cli-2.2.8.dist-info/RECORD
