Metadata-Version: 2.4
Name: appsentinels-cli
Version: 2.2.8
Summary: AppSentinels CLI - Modular API Security Management Tool with Plugin Architecture
Author-email: AppSentinels <support@appsentinels.com>
Project-URL: Homepage, https://github.com/vinay4appsentinels/appsentinels-cli
Project-URL: Bug Tracker, https://github.com/vinay4appsentinels/appsentinels-cli/issues
Project-URL: Documentation, https://docs.appsentinels.com/cli
Project-URL: Source Code, https://github.com/vinay4appsentinels/appsentinels-cli
Keywords: api,security,cli,appsentinels,oauth
Classifier: Development Status :: 4 - Beta
Classifier: Intended Audience :: Developers
Classifier: Intended Audience :: System Administrators
Classifier: License :: OSI Approved :: MIT License
Classifier: Operating System :: OS Independent
Classifier: Programming Language :: Python :: 3
Classifier: Programming Language :: Python :: 3.8
Classifier: Programming Language :: Python :: 3.9
Classifier: Programming Language :: Python :: 3.10
Classifier: Programming Language :: Python :: 3.11
Classifier: Programming Language :: Python :: 3.12
Classifier: Topic :: Internet :: WWW/HTTP :: Dynamic Content
Classifier: Topic :: Security
Classifier: Topic :: Software Development :: Libraries :: Python Modules
Classifier: Topic :: System :: Systems Administration
Classifier: Topic :: Utilities
Requires-Python: >=3.8
License-File: LICENSE
Requires-Dist: httpx>=0.24.0
Requires-Dist: click>=8.0.0
Requires-Dist: cryptography>=3.4.0
Requires-Dist: PyJWT>=2.4.0
Requires-Dist: pyyaml>=6.0
Requires-Dist: rich>=12.0.0
Requires-Dist: tabulate>=0.9.0
Requires-Dist: keyring>=24.0.0
Requires-Dist: python-dotenv>=1.0.0
Provides-Extra: dev
Requires-Dist: pytest>=7.0.0; extra == "dev"
Requires-Dist: pytest-asyncio>=0.21.0; extra == "dev"
Requires-Dist: black>=23.0.0; extra == "dev"
Requires-Dist: flake8>=6.0.0; extra == "dev"
Requires-Dist: mypy>=1.0.0; extra == "dev"
Provides-Extra: export
Requires-Dist: openpyxl>=3.1.0; extra == "export"
Requires-Dist: pandas>=2.0.0; extra == "export"
Provides-Extra: charts
Requires-Dist: matplotlib>=3.7.0; extra == "charts"
Requires-Dist: seaborn>=0.12.0; extra == "charts"
Dynamic: license-file
